kabigon/__init__.py
kabigon/api.py
kabigon/cli.py
kabigon/py.typed
kabigon/core/__init__.py
kabigon/core/exception.py
kabigon/core/loader.py
kabigon/loaders/__init__.py
kabigon/loaders/compose.py
kabigon/loaders/firecrawl.py
kabigon/loaders/github.py
kabigon/loaders/httpx.py
kabigon/loaders/pdf.py
kabigon/loaders/playwright.py
kabigon/loaders/ptt.py
kabigon/loaders/reddit.py
kabigon/loaders/reel.py
kabigon/loaders/truthsocial.py
kabigon/loaders/twitter.py
kabigon/loaders/utils.py
kabigon/loaders/youtube.py
kabigon/loaders/youtube_ytdlp.py
kabigon/loaders/ytdlp.py
kabigon-0.16.0.dist-info/METADATA
kabigon-0.16.0.dist-info/WHEEL
kabigon-0.16.0.dist-info/entry_points.txt
kabigon-0.16.0.dist-info/licenses/LICENSE
kabigon-0.16.0.dist-info/RECORD
