Metadata-Version: 2.4
Name: kabigon
Version: 0.16.0
Author-email: narumi <toucans-cutouts0f@icloud.com>
License-File: LICENSE
Requires-Python: >=3.12
Requires-Dist: charset-normalizer>=3.4.4
Requires-Dist: firecrawl-py>=4.13.4
Requires-Dist: httpx>=0.28.1
Requires-Dist: markdownify>=1.2.2
Requires-Dist: openai-whisper>=20250625
Requires-Dist: playwright>=1.57.0
Requires-Dist: pypdf>=6.6.0
Requires-Dist: rich>=14.3.1
Requires-Dist: typer>=0.21.1
Requires-Dist: youtube-transcript-api>=1.2.3
Requires-Dist: yt-dlp>=2025.12.8
